[
  {
    "week": "05.17-05.23",
    "file": "week-05.17-05.23.json",
    "generatedAt": "2026-05-25T12:31:20.786Z",
    "totalCount": 566,
    "categoryCount": 144,
    "industryCount": 10
  },
  {
    "week": "05.09-05.15",
    "file": "week-05.09-05.15.json",
    "generatedAt": "2026-05-16T08:25:17.510Z",
    "totalCount": 547,
    "categoryCount": 138,
    "industryCount": 10
  },
  {
    "week": "05.04-05.10",
    "file": "week-05.04-05.10.json",
    "generatedAt": "2026-05-11T08:44:28.175Z",
    "totalCount": 548,
    "categoryCount": 145,
    "industryCount": 9
  },
  {
    "week": "04.27-05.03",
    "file": "week-04.27-05.03.json",
    "generatedAt": "2026-05-04T14:15:48.007Z",
    "totalCount": 563,
    "categoryCount": 137,
    "industryCount": 9
  },
  {
    "week": "04.17-04.23",
    "file": "week-04.17-04.23.json",
    "generatedAt": "2026-04-24T13:51:47.046Z",
    "totalCount": 551,
    "categoryCount": 138,
    "industryCount": 9
  },
  {
    "week": "04.10-04.16",
    "file": "week-04.10-04.16.json",
    "generatedAt": "2026-04-24T13:51:46.756Z",
    "totalCount": 560,
    "categoryCount": 138,
    "industryCount": 9
  },
  {
    "week": "04.03-04.09",
    "file": "week-04.03-04.09.json",
    "generatedAt": "2026-04-10T08:47:03.449Z",
    "totalCount": 562,
    "categoryCount": 139,
    "industryCount": 10
  },
  {
    "week": "03.27-04.02",
    "file": "week-03.27-04.02.json",
    "generatedAt": "2026-04-03T04:53:47.457Z",
    "totalCount": 593,
    "categoryCount": 157,
    "industryCount": 10
  },
  {
    "week": "03.23-03.29",
    "file": "week-03.23-03.29.json",
    "generatedAt": "2026-03-31T03:05:18.330Z",
    "totalCount": 571,
    "categoryCount": 147,
    "industryCount": 10
  },
  {
    "week": "03.13-03.19",
    "file": "week-03.13-03.19.json",
    "generatedAt": "2026-03-20T14:30:01.028Z",
    "totalCount": 584,
    "categoryCount": 148,
    "industryCount": 9
  }
]
